nlip_sdk/Have you shared feedback with the client.md
nlip_sdk/__init__.py
nlip_sdk/errors.py
nlip_sdk/nlip.py
nlip_sdk/utils.py
nlip_sdk-0.1.2.dist-info/LICENSE
nlip_sdk-0.1.2.dist-info/METADATA
nlip_sdk-0.1.2.dist-info/WHEEL
nlip_sdk-0.1.2.dist-info/RECORD
