Metadata-Version: 2.3
Name: nlip_sdk
Version: 0.1.2
Summary: 
Author: Dinesh Verma
Author-email: dverma@us.ibm.com
Requires-Python: >=3.10,<4.0
Classifier: Programming Language :: Python :: 3
Classifier: Programming Language :: Python :: 3.10
Classifier: Programming Language :: Python :: 3.11
Classifier: Programming Language :: Python :: 3.12
Classifier: Programming Language :: Python :: 3.13
Requires-Dist: pydantic (>=2.9.2,<3.0.0)
